{"nodes": [{"id": "users_w_desktop_web_self_admin_web_packages_core_base_shared_src_utils_dom_ts", "label": "dom.ts", "file_type": "code", "source_file": "/Users/w/Desktop/web/self-admin-web/packages/@core/base/shared/src/utils/dom.ts", "source_location": "L1"}, {"id": "utils_dom_visibledomrect", "label": "VisibleDomRect", "file_type": "code", "source_file": "/Users/w/Desktop/web/self-admin-web/packages/@core/base/shared/src/utils/dom.ts", "source_location": "L1"}, {"id": "utils_dom_getelementvisiblerect", "label": "getElementVisibleRect()", "file_type": "code", "source_file": "/Users/w/Desktop/web/self-admin-web/packages/@core/base/shared/src/utils/dom.ts", "source_location": "L14"}, {"id": "utils_dom_getscrollbarwidth", "label": "getScrollbarWidth()", "file_type": "code", "source_file": "/Users/w/Desktop/web/self-admin-web/packages/@core/base/shared/src/utils/dom.ts", "source_location": "L66"}, {"id": "utils_dom_needsscrollbar", "label": "needsScrollbar()", "file_type": "code", "source_file": "/Users/w/Desktop/web/self-admin-web/packages/@core/base/shared/src/utils/dom.ts", "source_location": "L85"}, {"id": "utils_dom_triggerwindowresize", "label": "triggerWindowResize()", "file_type": "code", "source_file": "/Users/w/Desktop/web/self-admin-web/packages/@core/base/shared/src/utils/dom.ts", "source_location": "L101"}], "edges": [{"source": "users_w_desktop_web_self_admin_web_packages_core_base_shared_src_utils_dom_ts", "target": "utils_dom_visibledomrect", "relation": "contains", "confidence": "EXTRACTED", "source_file": "/Users/w/Desktop/web/self-admin-web/packages/@core/base/shared/src/utils/dom.ts", "source_location": "L1", "weight": 1.0}, {"source": "users_w_desktop_web_self_admin_web_packages_core_base_shared_src_utils_dom_ts", "target": "utils_dom_getelementvisiblerect", "relation": "contains", "confidence": "EXTRACTED", "source_file": "/Users/w/Desktop/web/self-admin-web/packages/@core/base/shared/src/utils/dom.ts", "source_location": "L14", "weight": 1.0}, {"source": "users_w_desktop_web_self_admin_web_packages_core_base_shared_src_utils_dom_ts", "target": "utils_dom_getscrollbarwidth", "relation": "contains", "confidence": "EXTRACTED", "source_file": "/Users/w/Desktop/web/self-admin-web/packages/@core/base/shared/src/utils/dom.ts", "source_location": "L66", "weight": 1.0}, {"source": "users_w_desktop_web_self_admin_web_packages_core_base_shared_src_utils_dom_ts", "target": "utils_dom_needsscrollbar", "relation": "contains", "confidence": "EXTRACTED", "source_file": "/Users/w/Desktop/web/self-admin-web/packages/@core/base/shared/src/utils/dom.ts", "source_location": "L85", "weight": 1.0}, {"source": "users_w_desktop_web_self_admin_web_packages_core_base_shared_src_utils_dom_ts", "target": "utils_dom_triggerwindowresize", "relation": "contains", "confidence": "EXTRACTED", "source_file": "/Users/w/Desktop/web/self-admin-web/packages/@core/base/shared/src/utils/dom.ts", "source_location": "L101", "weight": 1.0}], "raw_calls": [{"caller_nid": "utils_dom_getelementvisiblerect", "callee": "getBoundingClientRect", "is_member_call": true, "source_file": "/Users/w/Desktop/web/self-admin-web/packages/@core/base/shared/src/utils/dom.ts", "source_location": "L27"}, {"caller_nid": "utils_dom_getelementvisiblerect", "callee": "max", "is_member_call": true, "source_file": "/Users/w/Desktop/web/self-admin-web/packages/@core/base/shared/src/utils/dom.ts", "source_location": "L28"}, {"caller_nid": "utils_dom_getelementvisiblerect", "callee": "max", "is_member_call": true, "source_file": "/Users/w/Desktop/web/self-admin-web/packages/@core/base/shared/src/utils/dom.ts", "source_location": "L33"}, {"caller_nid": "utils_dom_getelementvisiblerect", "callee": "min", "is_member_call": true, "source_file": "/Users/w/Desktop/web/self-admin-web/packages/@core/base/shared/src/utils/dom.ts", "source_location": "L34"}, {"caller_nid": "utils_dom_getelementvisiblerect", "callee": "max", "is_member_call": true, "source_file": "/Users/w/Desktop/web/self-admin-web/packages/@core/base/shared/src/utils/dom.ts", "source_location": "L36"}, {"caller_nid": "utils_dom_getelementvisiblerect", "callee": "max", "is_member_call": true, "source_file": "/Users/w/Desktop/web/self-admin-web/packages/@core/base/shared/src/utils/dom.ts", "source_location": "L41"}, {"caller_nid": "utils_dom_getelementvisiblerect", "callee": "min", "is_member_call": true, "source_file": "/Users/w/Desktop/web/self-admin-web/packages/@core/base/shared/src/utils/dom.ts", "source_location": "L42"}, {"caller_nid": "utils_dom_getelementvisiblerect", "callee": "max", "is_member_call": true, "source_file": "/Users/w/Desktop/web/self-admin-web/packages/@core/base/shared/src/utils/dom.ts", "source_location": "L58"}, {"caller_nid": "utils_dom_getelementvisiblerect", "callee": "max", "is_member_call": true, "source_file": "/Users/w/Desktop/web/self-admin-web/packages/@core/base/shared/src/utils/dom.ts", "source_location": "L62"}, {"caller_nid": "utils_dom_getscrollbarwidth", "callee": "createElement", "is_member_call": true, "source_file": "/Users/w/Desktop/web/self-admin-web/packages/@core/base/shared/src/utils/dom.ts", "source_location": "L67"}, {"caller_nid": "utils_dom_getscrollbarwidth", "callee": "append", "is_member_call": true, "source_file": "/Users/w/Desktop/web/self-admin-web/packages/@core/base/shared/src/utils/dom.ts", "source_location": "L74"}, {"caller_nid": "utils_dom_getscrollbarwidth", "callee": "createElement", "is_member_call": true, "source_file": "/Users/w/Desktop/web/self-admin-web/packages/@core/base/shared/src/utils/dom.ts", "source_location": "L76"}, {"caller_nid": "utils_dom_getscrollbarwidth", "callee": "append", "is_member_call": true, "source_file": "/Users/w/Desktop/web/self-admin-web/packages/@core/base/shared/src/utils/dom.ts", "source_location": "L77"}, {"caller_nid": "utils_dom_getscrollbarwidth", "callee": "remove", "is_member_call": true, "source_file": "/Users/w/Desktop/web/self-admin-web/packages/@core/base/shared/src/utils/dom.ts", "source_location": "L81"}, {"caller_nid": "utils_dom_needsscrollbar", "callee": "getComputedStyle", "is_member_call": true, "source_file": "/Users/w/Desktop/web/self-admin-web/packages/@core/base/shared/src/utils/dom.ts", "source_location": "L90"}, {"caller_nid": "utils_dom_triggerwindowresize", "callee": "dispatchEvent", "is_member_call": true, "source_file": "/Users/w/Desktop/web/self-admin-web/packages/@core/base/shared/src/utils/dom.ts", "source_location": "L106"}]}